py_openthesaurus/__init__.py
py_openthesaurus/log.py
py_openthesaurus/main.py
py_openthesaurus/mysql_wrapper.py
py_openthesaurus/open_thesaurus.py
py_openthesaurus-1.0.5.dist-info/LICENSE
py_openthesaurus-1.0.5.dist-info/METADATA
py_openthesaurus-1.0.5.dist-info/WHEEL
py_openthesaurus-1.0.5.dist-info/entry_points.txt
py_openthesaurus-1.0.5.dist-info/top_level.txt
py_openthesaurus-1.0.5.dist-info/RECORD
