Metadata-Version: 2.1
Name: py-openthesaurus
Version: 1.0.5
Summary: Python wrapper for obtaining synonyms in the German language from OpenThesaurus
Home-page: https://github.com/Aid91/py_openthesaurus
Author: Aid Ahmetovic
Author-email: aidahmetovic91@gmail.com
License: MIT
Keywords: Natural Language Processing,NLP,German
Platform: UNKNOWN
Classifier: Development Status :: 5 - Production/Stable
Classifier: Intended Audience :: Developers
Classifier: Intended Audience :: Education
Classifier: Intended Audience :: Information Technology
Classifier: Intended Audience :: Science/Research
Classifier: Programming Language :: Python :: 3
Classifier: License :: OSI Approved :: MIT License
Classifier: Topic :: Text Processing :: General
Requires-Python: >=3.5
Requires-Dist: mysqlclient (==2.0.3)
